{
  "allowAppInstallation": {
    "minium_ios_version": null,
    "default_value": true,
    "label": "Allow installing of apps",
    "type" : "application"
  },
  "allowAssistant": {
    "minium_ios_version": null,
    "default_value": true,
    "label": "Allow Siri",
    "type" : "settings"
  },
  "allowAssistantWhileLocked": {
    "minium_ios_version": 5.1,
    "default_value": true,
    "label": "Allow Siri while device locked",
    "parent": "allowAssistant",
    "type" : "settings"
  },
  "allowCamera": {
    "minium_ios_version": null,
    "default_value": true,
    "label": "Allow use of camera",
    "type" : "settings"
  },
  "allowVideoConferencing": {
    "minium_ios_version": null,
    "default_value": true,
    "label": "Allow FaceTime",
    "parent": "allowCamera",
    "type" : "settings"
  },
  "allowChat": {
    "minium_ios_version": null,
    "default_value": true,
    "label": "Allow use of iMessage",
    "requires_supervised_device": true,
    "type" : "application"
  },
  "allowDiagnosticSubmission": {
    "minium_ios_version": 6,
    "default_value": true,
    "label": "Allow reporting of diagnostic information to Apple",
    "type" : "settings"
  },
  "allowExplicitContent": {
    "minium_ios_version": null,
    "default_value": true,
    "label": "Allow explicit content",
    "type" : "settings"
  },
  "allowGameCenter": {
    "minium_ios_version": 6,
    "default_value": true,
    "label": "Allow Game Center",
    "requires_supervised_device": true,
    "type" : "application"
  },
  "allowAddingGameCenterFriends": {
    "minium_ios_version": null,
    "default_value": true,
    "label": "Allow adding Game Center friends",
    "parent": "allowGameCenter",
    "type" : "application"
  },
  "allowMultiplayerGaming": {
    "minium_ios_version": null,
    "default_value": true,
    "label": "Allow multiplayer gaming",
    "parent": "allowGameCenter",
    "type" : "application"
  },
  "allowScreenShot": {
    "minium_ios_version": null,
    "default_value": true,
    "label": "Allow screen shot",
    "type" : "settings"
  },
  "allowYouTube": {
    "minium_ios_version": null,
    "default_value": true,
    "label": "Allow use of YouTube",
    "type" : "application"
  },
  "allowiTunes": {
    "minium_ios_version": null,
    "default_value": true,
    "label": "Allow use of iTunes Music Store",
    "type" : "application"
  },
  "forceITunesStorePasswordEntry": {
    "minium_ios_version": 5,
    "default_value": false,
    "label": "Require iTunes password for all purchases",
    "type" : "application"
  },
  "allowSafari": {
    "minium_ios_version": null,
    "default_value": true,
    "label": "Allow use of Safari",
    "type" : "application"
  },
  "allowUntrustedTLSPrompt": {
    "minium_ios_version": 5,
    "default_value": true,
    "label": "Allow accepting of untrusted TLS certificates",
    "type" : "application"
  },
  "allowCloudBackup": {
    "minium_ios_version": 5,
    "default_value": true,
    "label": "Allow iCloud backup",
    "type" : "application"
  },
  "allowCloudDocumentSync": {
    "minium_ios_version": 5,
    "default_value": true,
    "label": "Allow iCloud document syncing",
    "type" : "application"
  },
  "allowCloudKeychainSync": {
    "minium_ios_version": 7,
    "default_value": true,
    "label": "Allow keychain syncing to iCloud",
    "type" : "settings"
  },
  "allowPhotoStream": {
    "minium_ios_version": 5,
    "default_value": true,
    "label": "Allow Photo Stream (disallowing can cause data loss)",
    "type" : "settings"
  },
  "allowBookstore": {
    "minium_ios_version": 6,
    "default_value": true,
    "label": "Allow iBookstore",
    "requires_supervised_device": true,
    "type" : "application"
  },
  "allowBookstoreErotica": {
    "minium_ios_version": 6,
    "default_value": true,
    "label": "Allow Erotica",
    "parent": "allowBookstore",
    "type" : "application"
  },
  "allowPassbookWhileLocked": {
    "minium_ios_version": 6,
    "default_value": true,
    "label": "Allow Passbook while locked",
    "type" : "settings"
  },
  "allowSharedStream": {
    "minium_ios_version": 6,
    "default_value": true,
    "label": "Allow shared photo streams",
    "type" : "settings"
  },
  "allowUIConfigurationProfileInstallation": {
    "minium_ios_version": 6,
    "default_value": true,
    "label": "Allow installation of configuration profiles",
    "requires_supervised_device": true,
    "type" : "settings"
  },
  "allowGlobalBackgroundFetchWhenRoaming": {
    "minium_ios_version": null,
    "default_value": true,
    "label": "Allow background fetch while roaming",
    "type" : "settings"
  },
  "allowInAppPurchases": {
    "minium_ios_version": null,
    "default_value": true,
    "label": "Allow in-app purchases",
    "type" : "application"
  },
  "allowVoiceDialing": {
    "minium_ios_version": null,
    "default_value": true,
    "label": "Allow voice dialing",
    "type" : "settings"
  },
  "forceEncryptedBackup": {
    "minium_ios_version": null,
    "default_value": false,
    "label": "Force encrypted backups",
    "type" : "settings"
  },
  "safariAcceptCookies": {
    "minium_ios_version": null,
    "default_value": 2,
    "label": "Accept cookies",
    "possible_values": [
      [
        "Always",
        2
      ],
      [
        "From visited sites",
        1
      ],
      [
        "Never",
        0
      ]
    ],
    "parent": "allowSafari",
    "type": "application"
  },
  "safariAllowAutoFill": {
    "minium_ios_version": null,
    "default_value": true,
    "label": "Allow autofill",
    "parent": "allowSafari",
    "type": "application"
  },
  "safariAllowJavaScript": {
    "minium_ios_version": null,
    "default_value": true,
    "label": "Allow javascript",
    "parent": "allowSafari",
    "type": "application"
  },
  "safariAllowPopups": {
    "minium_ios_version": null,
    "default_value": true,
    "label": "Allow popups",
    "parent": "allowSafari",
    "type": "application"
  },
  "safariForceFraudWarning": {
    "minium_ios_version": null,
    "default_value": false,
    "label": "Force fraud warning",
    "parent": "allowSafari",
    "type": "application"
  },
  "allowAccountModification": {
    "minium_ios_version": 7,
    "default_value": true,
    "label": "Allow account modification",
    "requires_supervised_device": true,
    "type": "settings"
  },
  "allowAirDrop": {
    "minium_ios_version": 7,
    "default_value": true,
    "label": "Allow AirDrop",
    "requires_supervised_device": true,
    "type": "application"
  },
  "allowAssistantUserGeneratedContent": {
    "minium_ios_version": 7,
    "default_value": true,
    "label": "Allow Siri to query user-generated content from the web",
    "requires_supervised_device": true,
    "type": "application"
  },
  "allowAppCellularDataModification": {
    "minium_ios_version": 7,
    "default_value": true,
    "label": "Allow changes to cellular data usage settings",
    "requires_supervised_device": true,
    "type": "settings"
  },
  "allowFindMyFriendsModification": {
    "minium_ios_version": 7,
    "default_value": true,
    "label": "Allow find my friends modification",
    "requires_supervised_device": true,
    "type": "application"
  },
  "allowFingerprintForUnlock": {
    "minium_ios_version": 7,
    "default_value": true,
    "label": "Allow Touch ID to unlock the device",
    "type": "settings"
  },
  "allowHostPairing": {
    "minium_ios_version": 7,
    "default_value": false,
    "label": "Allow pairing with hosts other than the supervision host",
    "requires_supervised_device": true,
    "type": "settings"
  },
  "allowLockScreenControlCenter": {
    "minium_ios_version": 7,
    "default_value": true,
    "label": "Allow Control Center access from the lock screen",
    "type": "settings"
  },
  "allowLockScreenNotificationsView": {
    "minium_ios_version": 7,
    "default_value": true,
    "label": "Allow Notifications view in Notification Center on the lock screen",
    "type": "settings"
  },
  "allowLockScreenTodayView": {
    "minium_ios_version": 7,
    "default_value": true,
    "label": "Allow Today view in Notification Center on the lock screen",
    "type": "settings"
  },
  "allowOpenFromManagedToUnmanaged": {
    "minium_ios_version": 7,
    "default_value": true,
    "label": "Allow documents in managed apps and accounts to open in unmanaged apps and accounts",
    "type": "settings"
  },
  "allowOpenFromUnmanagedToManaged": {
    "minium_ios_version": 7,
    "default_value": true,
    "label": "Allow documents in unmanaged apps and accounts to open in managed apps and accounts",
    "type": "settings"
  },
  "allowOTAPKIUpdates": {
    "minium_ios_version": 7,
    "default_value": true,
    "label": "Allow over-the-air PKI updates",
    "type": "settings"
  },
  "forceLimitAdTracking": {
    "minium_ios_version": 7,
    "default_value": false,
    "label": "Force limited ad-tracking",
    "type": "settings"
  }
}
